smart_srt_translator/__init__.py
smart_srt_translator/api.py
smart_srt_translator/cli.py
smart_srt_translator/env.py
smart_srt_translator/io_json.py
smart_srt_translator/models.py
smart_srt_translator/smart_pipeline.py
smart_srt_translator/srt_utils.py
smart_srt_translator/providers/__init__.py
smart_srt_translator/providers/base.py
smart_srt_translator/providers/dummy_provider.py
smart_srt_translator/providers/openai_provider.py
smart_srt_translator-0.1.3.dist-info/METADATA
smart_srt_translator-0.1.3.dist-info/WHEEL
smart_srt_translator-0.1.3.dist-info/entry_points.txt
smart_srt_translator-0.1.3.dist-info/top_level.txt
smart_srt_translator-0.1.3.dist-info/RECORD
