Metadata-Version: 2.4
Name: smart-srt-translator
Version: 0.1.3
Summary: Smart SRT subtitle translation with optional audio probing and provider abstraction
Author: Project Contributors
License: MIT
Project-URL: Homepage, https://github.com/ddumdi11/smart-srt-translator
Project-URL: Repository, https://github.com/ddumdi11/smart-srt-translator.git
Project-URL: Issues, https://github.com/ddumdi11/smart-srt-translator/issues
Project-URL: Changelog, https://pypi.org/project/smart-srt-translator/#history
Keywords: srt,subtitle,translation,openai
Classifier: Programming Language :: Python :: 3
Classifier: License :: OSI Approved :: MIT License
Classifier: Operating System :: OS Independent
Requires-Python: >=3.11
Provides-Extra: openai
Requires-Dist: openai>=1.0.0; extra == "openai"
